{
  "ticker": "VIB",
  "companyName": "Ngân hàng Thương mại Cổ phần Quốc tế Việt Nam",
  "analysis_comments": {
    "ytd_loans_growth": 1.13,
    "ytd_dep_growth": 5.5,
    "profit_source_comment": "Lợi nhuận ghi nhận sự đóng góp lớn từ các khoản thu nhập ngoài lãi đột biến (chiếm 31.1% tổng thu nhập HĐ), cho thấy nguồn lợi nhuận không hoàn toàn đi liền với hoạt động tín dụng cốt lõi.",
    "provision_comment": "Chi phí trích lập dự phòng duy trì ở mức 43.0% LNTT, cho thấy ngân hàng tiếp tục trích lập thận trọng bảo vệ chất lượng tài sản, không lạm dụng cắt giảm dự phòng để làm đẹp lợi nhuận.",
    "nii_latest_val": 4038.57,
    "npat_latest_val": 2241.19
  },
  "credit_funding_growth": {
    "quarters": [
      "Q2/18",
      "Q3/18",
      "Q4/18",
      "Q1/19",
      "Q2/19",
      "Q3/19",
      "Q4/19",
      "Q1/20",
      "Q2/20",
      "Q3/20",
      "Q4/20",
      "Q1/21",
      "Q2/21",
      "Q3/21",
      "Q4/21",
      "Q1/22",
      "Q2/22",
      "Q3/22",
      "Q4/22",
      "Q1/23",
      "Q2/23",
      "Q3/23",
      "Q4/23",
      "Q1/24",
      "Q2/24",
      "Q3/24",
      "Q4/24",
      "Q1/25",
      "Q2/25",
      "Q3/25",
      "Q4/25",
      "Q1/26"
    ],
    "credit_absolute": [
      87706.7,
      89730.3,
      95303.2,
      100912.1,
      113429.0,
      122008.4,
      127984.4,
      133509.8,
      136318.9,
      147500.7,
      167840.2,
      175649.4,
      181013.2,
      185746.2,
      199158.8,
      211512.9,
      218827.0,
      223326.0,
      228921.6,
      226046.7,
      231389.4,
      241933.1,
      262116.6,
      262953.2,
      274038.6,
      292188.6,
      318358.5,
      329306.5,
      351402.5,
      367905.8,
      377113.2,
      381362.0
    ],
    "funding_absolute": [
      82885.6,
      88978.3,
      95015.1,
      99123.0,
      114415.4,
      128964.4,
      139511.9,
      140817.4,
      147774.8,
      165710.2,
      178919.4,
      185354.2,
      197336.3,
      197727.9,
      215863.1,
      226563.9,
      237871.3,
      224222.3,
      231898.8,
      233108.2,
      233578.9,
      240012.9,
      263176.3,
      261187.8,
      266305.1,
      280182.7,
      302402.5,
      311756.2,
      337488.7,
      339271.9,
      335619.0,
      361024.7
    ],
    "credit_ytd": [
      3.42,
      2.31,
      6.21,
      5.89,
      12.4,
      7.56,
      4.9,
      4.32,
      2.1,
      8.2,
      13.79,
      4.65,
      3.05,
      2.61,
      7.22,
      6.2,
      3.46,
      2.06,
      2.51,
      -1.26,
      2.36,
      4.56,
      8.34,
      0.32,
      4.22,
      6.62,
      8.96,
      3.44,
      6.71,
      4.7,
      2.5,
      1.13
    ],
    "funding_ytd": [
      0.74,
      7.35,
      6.78,
      4.32,
      15.43,
      12.72,
      8.18,
      0.94,
      4.94,
      12.14,
      7.97,
      3.6,
      6.46,
      0.2,
      9.17,
      4.96,
      4.99,
      -5.74,
      3.42,
      0.52,
      0.2,
      2.75,
      9.65,
      -0.76,
      1.96,
      5.21,
      7.93,
      3.09,
      8.25,
      0.53,
      -1.08,
      7.57
    ]
  },
  "sector": "Ngân hàng",
  "currentPrice": 16150.0,
  "marketCap": 54974692055000.0,
  "shares": 3404005700,
  "assumptions": {
    "loans_growth": [
      14.0,
      13.0,
      12.0
    ],
    "dep_growth": [
      12.0,
      11.0,
      10.0
    ],
    "nim": [
      3.28,
      3.37,
      3.43
    ],
    "cir": [
      33.0,
      32.0,
      32.0
    ],
    "coc": [
      0.95,
      0.9,
      0.85
    ],
    "npl": [
      2.86,
      2.71,
      2.56
    ]
  },
  "financial_snapshot": {
    "years": [
      "2023",
      "2024",
      "2025",
      "2026F",
      "2027F",
      "2028F"
    ],
    "nii": [
      18484.1,
      16750.4,
      16092.2,
      19045.8,
      22008.5,
      24970.0
    ],
    "toi": [
      22160.5,
      20569.1,
      20006.6,
      23547.4,
      27185.4,
      30871.7
    ],
    "npat": [
      8563.1,
      7204.5,
      7285.4,
      9554.7,
      11492.3,
      13292.6
    ],
    "nim": [
      5.04,
      3.78,
      3.12,
      3.28,
      3.37,
      3.43
    ],
    "roe": [
      24.3,
      18.1,
      16.4,
      19.01,
      19.95,
      20.05
    ],
    "ldr": [
      103.5,
      108.3,
      117.8,
      119.54,
      122.68,
      125.76
    ],
    "npl": [
      3.2,
      3.57,
      3.01,
      2.86,
      2.71,
      2.56
    ]
  },
  "forecast_text": {
    "loans_g_26": 14.0,
    "dep_g_26": 12.0,
    "nim_26": 3.28,
    "coc_26": 0.95,
    "cir_26": 33.0,
    "nim_trend": "tăng nhẹ",
    "coc_trend": "giảm dần nhờ chất lượng tài sản cải thiện"
  },
  "gdriveExcelUrl": "https://docs.google.com/spreadsheets/d/1svyQ_PbD2zVp9C0W0nNSBifZaTKjRE3L/edit?usp=drivesdk&ouid=101157630370734895433&rtpof=true&sd=true",
  "gdrivePdfUrl": "https://drive.google.com/file/d/1zS9AX8TV2YAHZ-qli_9B460HmHmIPf2_/view?usp=drivesdk",
  "pe_hist": [
    8.0830990662,
    9.0175849713,
    8.1589111122,
    8.0965147871,
    7.2381006027
  ],
  "pb_hist": [
    1.3242610736,
    1.5604776374,
    1.3650690329,
    1.2591371432,
    1.1186434314
  ],
  "pe_quarters": [
    10.8404066634,
    8.6097537634,
    6.7369145928,
    6.7946987686,
    5.6456248765,
    5.9902457908,
    5.0097999806,
    4.2397969301,
    5.1957877959,
    8.3521689341,
    9.1080981078,
    13.0956663006,
    14.6204119762,
    11.8410566023,
    10.0316192382,
    7.5122704978,
    5.6887744772,
    5.5206208614,
    5.1658114065,
    5.772929156,
    5.5443837974,
    6.0018846541,
    6.9812717748,
    6.4216107143,
    7.334694021,
    8.016820841,
    7.6111809076,
    8.0830990662,
    9.0175849713,
    8.1589111122,
    8.0965147871,
    7.2381006027
  ],
  "pb_quarters": [
    1.7099060254,
    1.5164805477,
    1.327130287,
    1.3404628245,
    1.2713374958,
    1.445698406,
    1.295482365,
    1.0312172904,
    1.2754079035,
    2.0286368471,
    2.2855458137,
    3.382390309,
    3.9540347287,
    3.04200176,
    2.6471042014,
    1.9689948548,
    1.4697924308,
    1.5248567286,
    1.342670695,
    1.5655259495,
    1.4700234275,
    1.4816914574,
    1.5779997237,
    1.4065594356,
    1.479837028,
    1.4469720249,
    1.3130084318,
    1.3242610736,
    1.5604776374,
    1.3650690329,
    1.2591371432,
    1.1186434314
  ],
  "quarter_labels": [
    "2018-Q1",
    "2018-Q2",
    "2018-Q3",
    "2018-Q4",
    "2019-Q1",
    "2019-Q2",
    "2019-Q3",
    "2019-Q4",
    "2020-Q1",
    "2020-Q2",
    "2020-Q3",
    "2020-Q4",
    "2021-Q1",
    "2021-Q3",
    "2021-Q4",
    "2022-Q1",
    "2022-Q2",
    "2022-Q3",
    "2022-Q4",
    "2023-Q1",
    "2023-Q2",
    "2023-Q3",
    "2023-Q4",
    "2024-Q1",
    "2024-Q2",
    "2024-Q3",
    "2024-Q4",
    "2025-Q1",
    "2025-Q2",
    "2025-Q3",
    "2025-Q4",
    "2026-Q1"
  ],
  "income_quarterly": [
    {
      "quarter": "2023-Q2",
      "nii": 4401.86,
      "nonii": 962.04,
      "toi": 5363.9,
      "ppop": 3808.16,
      "npat": 2358.4
    },
    {
      "quarter": "2023-Q3",
      "nii": 4673.19,
      "nonii": 1351.31,
      "toi": 6024.5,
      "ppop": 4307.58,
      "npat": 2146.9
    },
    {
      "quarter": "2023-Q4",
      "nii": 4333.29,
      "nonii": 1509.2,
      "toi": 5842.49,
      "ppop": 4071.93,
      "npat": 1902.01
    },
    {
      "quarter": "2024-Q1",
      "nii": 4357.79,
      "nonii": 960.72,
      "toi": 5318.51,
      "ppop": 3447.42,
      "npat": 2001.14
    },
    {
      "quarter": "2024-Q2",
      "nii": 4316.91,
      "nonii": 722.28,
      "toi": 5039.19,
      "ppop": 3233.0,
      "npat": 1682.96
    },
    {
      "quarter": "2024-Q3",
      "nii": 4159.34,
      "nonii": 776.64,
      "toi": 4935.98,
      "ppop": 3153.72,
      "npat": 1599.17
    },
    {
      "quarter": "2024-Q4",
      "nii": 3916.36,
      "nonii": 1359.01,
      "toi": 5275.37,
      "ppop": 3523.63,
      "npat": 1921.19
    },
    {
      "quarter": "2025-Q1",
      "nii": 3737.11,
      "nonii": 864.05,
      "toi": 4601.15,
      "ppop": 2842.12,
      "npat": 1936.46
    },
    {
      "quarter": "2025-Q2",
      "nii": 3968.69,
      "nonii": 1148.12,
      "toi": 5116.82,
      "ppop": 3231.2,
      "npat": 2076.47
    },
    {
      "quarter": "2025-Q3",
      "nii": 4172.73,
      "nonii": 834.31,
      "toi": 5007.03,
      "ppop": 3187.87,
      "npat": 1624.51
    },
    {
      "quarter": "2025-Q4",
      "nii": 4213.63,
      "nonii": 1068.01,
      "toi": 5281.64,
      "ppop": 3310.44,
      "npat": 1647.98
    },
    {
      "quarter": "2026-Q1",
      "nii": 4038.57,
      "nonii": 1821.77,
      "toi": 5860.34,
      "ppop": 4007.59,
      "npat": 2241.19
    }
  ],
  "ratios_quarterly": {
    "quarters": [
      "2023-Q2",
      "2023-Q3",
      "2023-Q4",
      "2024-Q1",
      "2024-Q2",
      "2024-Q3",
      "2024-Q4",
      "2025-Q1",
      "2025-Q2",
      "2025-Q3",
      "2025-Q4",
      "2026-Q1"
    ],
    "nim": [
      0.0761,
      0.0773,
      0.0661,
      0.0663,
      0.063,
      0.0569,
      0.0492,
      0.0454,
      0.0452,
      0.0454,
      0.0447,
      0.0424
    ],
    "ldr": [
      1.003,
      1.0204,
      1.0061,
      1.0214,
      1.0393,
      1.0524,
      1.0626,
      1.0687,
      1.0533,
      1.0979,
      1.144,
      1.0861
    ],
    "casa": [
      0.1196,
      0.1277,
      0.132,
      0.1322,
      0.1466,
      0.1353,
      0.1395,
      0.1495,
      0.1661,
      0.1528,
      0.1439,
      0.1393
    ],
    "npl": [
      3.69,
      3.74,
      3.2,
      3.66,
      3.72,
      3.92,
      3.57,
      3.85,
      3.6,
      3.37,
      3.01,
      2.98
    ],
    "llr": [
      39.1,
      41.4,
      51.0,
      49.8,
      48.1,
      47.1,
      50.1,
      38.6,
      37.2,
      39.4,
      42.9,
      43.1
    ],
    "roe": [
      0.2782,
      0.2383,
      0.2005,
      0.2084,
      0.1755,
      0.1601,
      0.1836,
      0.1775,
      0.1904,
      0.1436,
      0.1405,
      0.1824
    ],
    "credit_growth": [
      1.08,
      5.68,
      14.5,
      0.32,
      4.55,
      11.47,
      21.46,
      3.44,
      10.38,
      15.57,
      18.47,
      1.13
    ]
  },
  "earning_assets_quarterly": {
    "quarters": [
      "2023-Q2",
      "2023-Q3",
      "2023-Q4",
      "2024-Q1",
      "2024-Q2",
      "2024-Q3",
      "2024-Q4",
      "2025-Q1",
      "2025-Q2",
      "2025-Q3",
      "2025-Q4",
      "2026-Q1"
    ],
    "cash_sbv": [
      7656.6,
      5867.1,
      9898.8,
      5463.5,
      7533.8,
      6593.0,
      11548.4,
      7363.9,
      7044.2,
      9859.4,
      12550.6,
      6189.3
    ],
    "bank_dep": [
      79806.1,
      74707.1,
      68197.6,
      92771.8,
      114455.7,
      82657.1,
      105588.5,
      102269.0,
      97946.4,
      104756.6,
      104411.1,
      114132.2
    ],
    "loans": [
      231347.0,
      241890.7,
      262074.2,
      262910.8,
      273996.2,
      292146.2,
      318316.1,
      329264.1,
      351360.1,
      367863.4,
      377113.2,
      381362.0
    ],
    "inv_sec": [
      50259.4,
      52384.6,
      60988.4,
      44298.4,
      28742.1,
      57909.6,
      50344.3,
      49438.6,
      67210.4,
      53170.1,
      51149.5,
      49089.1
    ]
  },
  "loan_industry": {
    "quarters": [
      "2023-Q2",
      "2023-Q3",
      "2023-Q4",
      "2024-Q1",
      "2024-Q2",
      "2024-Q3",
      "2024-Q4",
      "2025-Q1",
      "2025-Q2",
      "2025-Q3",
      "2025-Q4",
      "2026-Q1"
    ],
    "real_estate": [
      27257.7,
      30503.3,
      35366.1,
      35650.2,
      42308.1,
      51182.9,
      58132.1,
      65601.6,
      78929.2,
      93053.2,
      105472.6,
      113664.3
    ],
    "individuals": [
      201509.5,
      209028.3,
      224800.9,
      224987.9,
      227588.8,
      237064.4,
      254572.9,
      257155.0,
      264303.2,
      266909.3,
      266644.0,
      262676.2
    ],
    "wholesale_retail": [
      0.4,
      0.4,
      0.4,
      0.3,
      0.3,
      13.5,
      13.4,
      36.2,
      36.2,
      0.2,
      2.0,
      1.8
    ],
    "others": [
      2579.4,
      2358.7,
      1906.8,
      2272.4,
      4098.9,
      3885.4,
      5597.6,
      6471.2,
      8091.5,
      7900.7,
      4994.7,
      5019.7
    ]
  },
  "npl_groups": {
    "quarters": [
      "2023-Q2",
      "2023-Q3",
      "2023-Q4",
      "2024-Q1",
      "2024-Q2",
      "2024-Q3",
      "2024-Q4",
      "2025-Q1",
      "2025-Q2",
      "2025-Q3",
      "2025-Q4",
      "2026-Q1"
    ],
    "group1": [
      211092.0,
      220748.9,
      243146.7,
      242962.6,
      256271.6,
      275242.7,
      301905.6,
      310436.4,
      333057.9,
      350150.7,
      361491.1,
      365055.1
    ],
    "group2": [
      15057.4,
      15841.5,
      14824.2,
      15112.8,
      12433.2,
      10845.8,
      10730.6,
      11046.7,
      10343.0,
      10204.1,
      9146.2,
      9845.0
    ],
    "group3": [
      3149.0,
      3057.6,
      2479.3,
      2529.7,
      2266.8,
      2265.1,
      2305.5,
      2905.9,
      2567.1,
      2428.2,
      2149.2,
      2311.8
    ],
    "group4": [
      3539.3,
      4673.1,
      3697.1,
      3538.1,
      3728.9,
      3210.1,
      2670.6,
      2986.4,
      3502.5,
      3480.4,
      2824.2,
      2932.0
    ],
    "group5": [
      1840.4,
      1308.9,
      2198.1,
      3565.4,
      4205.5,
      5986.1,
      6397.4,
      6782.8,
      6595.6,
      6472.6,
      6361.3,
      6113.4
    ]
  },
  "loan_terms": {
    "quarters": [
      "2023-Q2",
      "2023-Q3",
      "2023-Q4",
      "2024-Q1",
      "2024-Q2",
      "2024-Q3",
      "2024-Q4",
      "2025-Q1",
      "2025-Q2",
      "2025-Q3",
      "2025-Q4",
      "2026-Q1"
    ],
    "short_term": [
      77768.3,
      86068.1,
      102695.8,
      105267.6,
      113738.8,
      125465.6,
      142051.3,
      151074.6,
      162730.7,
      163849.9,
      158864.4,
      159418.7
    ],
    "medium_term": [
      15686.5,
      15247.9,
      15123.4,
      14238.6,
      16521.5,
      18253.4,
      20244.7,
      22018.9,
      25978.0,
      34047.1,
      43794.7,
      48365.7
    ],
    "long_term": [
      141223.4,
      144314.0,
      148526.4,
      148202.5,
      148645.8,
      153830.7,
      161713.7,
      161064.7,
      167357.4,
      174839.1,
      179312.9,
      178472.9
    ]
  },
  "deposit_types": {
    "quarters": [
      "2023-Q2",
      "2023-Q3",
      "2023-Q4",
      "2024-Q1",
      "2024-Q2",
      "2024-Q3",
      "2024-Q4",
      "2025-Q1",
      "2025-Q2",
      "2025-Q3",
      "2025-Q4",
      "2026-Q1"
    ],
    "casa": [
      24563.8,
      27269.3,
      31229.7,
      30962.7,
      36312.1,
      34596.3,
      38534.5,
      42205.8,
      50571.9,
      47049.8,
      42377.9,
      44063.8
    ],
    "term": [
      180389.8,
      185752.4,
      204957.9,
      202914.9,
      210798.6,
      220692.9,
      237301.0,
      239585.3,
      253260.7,
      260373.3,
      251612.1,
      271563.1
    ],
    "others": [
      349.1,
      512.0,
      389.6,
      333.2,
      519.1,
      343.4,
      472.9,
      507.0,
      560.3,
      506.1,
      587.6,
      746.9
    ]
  },
  "earning_assets": {
    "years": [
      "2021",
      "2022",
      "2023",
      "2024",
      "2025"
    ],
    "cash_sbv": [
      26412.3,
      11680.6,
      9898.8,
      11548.4,
      12550.6
    ],
    "bank_dep": [
      27985.1,
      51899.8,
      68197.6,
      105588.5,
      104411.1
    ],
    "loans": [
      199116.4,
      228879.2,
      262075.0,
      318316.1,
      377113.2
    ],
    "inv_sec": [
      44737.2,
      40278.7,
      60988.4,
      50344.3,
      51149.5
    ]
  },
  "thesis": [
    "Ngân hàng Thương mại Cổ phần Quốc tế Việt Nam (VIB) duy trì mô hình kinh doanh tập trung mạnh vào phân khúc khách hàng cá nhân cao cấp và cho vay bất động sản (chiếm tỷ trọng lớn trong cơ cấu tín dụng",
    "Sức khỏe tài chính của VIB nhìn chung ở mức tốt với tỷ lệ nợ xấu NPL được kiểm soát thấp và tỷ lệ bao phủ nợ xấu (LLR) vượt trội hoặc tương đương mức trung bình ngành. Tốc độ tăng trưởng tín dụng và h",
    "Với giá hiện tại và giá mục tiêu ước tính từ mô hình định giá hỗn hợp, cổ phiếu VIB mang lại triển vọng tăng giá hấp dẫn (upside lớn). Đây là cơ hội đầu tư đáng cân nhắc cho mục tiêu dài hạn nhờ vị th"
  ],
  "risks": [
    "Rủi ro NIM thu hẹp: cạnh tranh lãi suất cho vay trong bối cảnh NHNN giảm lãi suất — NIM có thể giảm 0.31% so kế hoạch.",
    "Rủi ro nợ xấu: thị trường bất động sản hồi phục chậm, nợ nhóm 2 tăng có thể chuyển thành NPL trong 6–12 tháng.",
    "Rủi ro pháp lý: Thông tư siết TPDN và nâng chuẩn CAR có thể hạn chế room tín dụng của VIB."
  ],
  "moats": {
    "Network Effect": {
      "score": 4,
      "desc": "Mạng lưới khách hàng VIB rộng — hiệu ứng mạng lưới tạo CASA ổn định."
    },
    "Cost Advantage": {
      "score": 3,
      "desc": "CASA cao giúp COF thấp hơn ngành, tạo lợi thế chi phí vốn bền vững."
    },
    "Switching Cost": {
      "score": 3,
      "desc": "Hệ sinh thái ứng dụng số tích hợp tạo rào cản chuyển đổi khách hàng."
    },
    "Intangible Assets": {
      "score": 4,
      "desc": "Thương hiệu ngân hàng uy tín và quan hệ doanh nghiệp/cá nhân lâu năm."
    },
    "Efficient Scale": {
      "score": 3,
      "desc": "Quy mô tài sản tạo hiệu quả vận hành trên chi phí cố định hạ tầng CNTT."
    }
  },
  "pestle": [
    {
      "factor": "Political",
      "content": "Môi trường chính trị ổn định, NHNN điều hành linh hoạt hỗ trợ tăng trưởng tín dụng.",
      "impact": "Positive"
    },
    {
      "factor": "Economic",
      "content": "GDP 6–7%, nhu cầu tín dụng sản xuất–tiêu dùng cao, lãi suất huy động dần giảm.",
      "impact": "Positive"
    },
    {
      "factor": "Social",
      "content": "Tầng lớp trung lưu mở rộng, thanh toán không tiền mặt thúc đẩy CASA và dịch vụ phí.",
      "impact": "Positive"
    },
    {
      "factor": "Technological",
      "content": "Chuyển đổi số banking giảm CIR, tăng CASA và cross-sell — đây là lợi thế cạnh tranh dài hạn.",
      "impact": "Positive"
    },
    {
      "factor": "Legal",
      "content": "Thông tư 06/2024 siết TPDN, Basel II/III nâng chuẩn CAR — tạo áp lực pháp lý ngắn hạn.",
      "impact": "Neutral"
    },
    {
      "factor": "Environmental",
      "content": "ESG lending ngày càng được yêu cầu; rủi ro tín dụng BĐS liên quan biến đổi khí hậu tăng.",
      "impact": "Negative"
    }
  ],
  "valuation": {
    "weightedTarget": 26646,
    "upside": 64.99,
    "bear": 22648,
    "base": 26645,
    "bull": 30642,
    "pbAttractive": 1.32,
    "pbAttractivePrice": 21976,
    "pbTarget": 1.68,
    "pbTargetPrice": 27814,
    "COE": 12.1,
    "peMedian": 7.29,
    "pbMedian": 1.47,
    "bvpsBase": 13779,
    "riValue": 28911,
    "pbValue": 24380,
    "pvRi": 3164,
    "pvCv": 11968,
    "epsFc": [
      2807,
      3376,
      3905
    ],
    "riResults": [
      1140,
      1369,
      1490
    ],
    "recommend": "MUA"
  },
  "comments": {
    "businessModel": "Ngân hàng Thương mại Cổ phần Quốc tế Việt Nam (VIB) duy trì mô hình kinh doanh tập trung mạnh vào phân khúc khách hàng cá nhân cao cấp và cho vay bất động sản (chiếm tỷ trọng lớn trong cơ cấu tín dụng). Chiến lược này đi kèm vị thế dẫn đầu về tỷ lệ CASA và nền tảng ngân hàng số vượt trội.",
    "financialPerformance": "Sức khỏe tài chính của VIB nhìn chung ở mức tốt với tỷ lệ nợ xấu NPL được kiểm soát thấp và tỷ lệ bao phủ nợ xấu (LLR) vượt trội hoặc tương đương mức trung bình ngành. Tốc độ tăng trưởng tín dụng và hiệu quả sinh lời (ROE, NIM) tiếp tục duy trì vị thế nhóm đầu thị trường.",
    "valuationText": "Với giá hiện tại và giá mục tiêu ước tính từ mô hình định giá hỗn hợp, cổ phiếu VIB mang lại triển vọng tăng giá hấp dẫn (upside lớn). Đây là cơ hội đầu tư đáng cân nhắc cho mục tiêu dài hạn nhờ vị thế đầu ngành vững chắc."
  },
  "data": {
    "years": [
      2021,
      2022,
      2023,
      2024,
      2025,
      2026,
      2027,
      2028
    ],
    "revenue": [
      11816.15,
      14962.56,
      18484.07,
      16750.41,
      16092.16,
      19045.78,
      22008.46,
      24969.99
    ],
    "npat": [
      6409.75,
      8468.77,
      8563.05,
      7204.47,
      7285.43,
      9554.74,
      11492.29,
      13292.56
    ],
    "eps": [
      4127.0,
      4018.1,
      3375.5,
      2418.3,
      2140.3,
      2806.9,
      3376.1,
      3905.0
    ],
    "equity": [
      24290.74,
      32651.04,
      37939.59,
      41861.81,
      46904.74,
      53593.06,
      61637.66,
      70942.45
    ]
  },
  "ratios": {
    "nim": [
      0.0396,
      0.0474,
      0.0504,
      0.0378,
      0.0312,
      0.0328,
      0.0337,
      0.0343
    ],
    "roe": [
      0.2639,
      0.2975,
      0.2426,
      0.1806,
      0.1641,
      null,
      null,
      null
    ],
    "roa": [
      0.0207,
      0.0247,
      0.0209,
      0.0146,
      0.0131,
      null,
      null,
      null
    ],
    "npl": [
      0.0235,
      0.0248,
      0.032,
      0.0357,
      0.0301,
      0.0286,
      0.0271,
      0.0256
    ],
    "ldr": [
      0.9638,
      1.023,
      1.0349,
      1.0828,
      1.1783,
      null,
      null,
      null
    ],
    "casa": [
      0.1611,
      0.1364,
      0.132,
      0.1395,
      0.1439,
      0.1539,
      0.1639,
      0.1739
    ]
  }
}